codeclone/__init__.py
codeclone/baseline.py
codeclone/blockhash.py
codeclone/blocks.py
codeclone/cache.py
codeclone/cfg.py
codeclone/cli.py
codeclone/extractor.py
codeclone/fingerprint.py
codeclone/html_report.py
codeclone/normalize.py
codeclone/report.py
codeclone/scanner.py
codeclone-1.1.0.dist-info/licenses/LICENSE
codeclone-1.1.0.dist-info/METADATA
codeclone-1.1.0.dist-info/WHEEL
codeclone-1.1.0.dist-info/entry_points.txt
codeclone-1.1.0.dist-info/top_level.txt
codeclone-1.1.0.dist-info/RECORD
