Metadata-Version: 2.4
Name: codeclone
Version: 1.1.0
Summary: AST and CFG-based code clone detector for Python focused on architectural duplication
Author-email: Den Rozhnovskiy <pytelemonbot@mail.ru>
Maintainer-email: Den Rozhnovskiy <pytelemonbot@mail.ru>
License: MIT
Project-URL: Homepage, https://github.com/orenlab/codeclone
Project-URL: Repository, https://github.com/orenlab/codeclone
Project-URL: Issues, https://github.com/orenlab/codeclone/issues
Project-URL: Changelog, https://github.com/orenlab/codeclone/releases
Project-URL: Documentation, https://github.com/orenlab/codeclone/tree/main/docs
Keywords: python,ast,code-clone,duplication,static-analysis,ci,architecture
Classifier: Development Status :: 5 - Production/Stable
Classifier: Intended Audience :: Developers
Classifier: Topic :: Software Development :: Quality Assurance
Classifier: Topic :: Software Development :: Code Generators
Classifier: Topic :: Software Development :: Testing
Classifier: Typing :: Typed
Classifier: License :: OSI Approved :: MIT License
Classifier: Programming Language :: Python :: 3
Classifier: Programming Language :: Python :: 3.10
Classifier: Programming Language :: Python :: 3.11
Classifier: Programming Language :: Python :: 3.12
Classifier: Programming Language :: Python :: 3.13
Classifier: Operating System :: OS Independent
Requires-Python: >=3.10
License-File: LICENSE
Requires-Dist: pygments>=2.19.2
Provides-Extra: dev
Requires-Dist: pytest>=9.0.0; extra == "dev"
Requires-Dist: build>=1.2.0; extra == "dev"
Requires-Dist: twine>=5.0.0; extra == "dev"
Requires-Dist: mypy>=1.19.1; extra == "dev"
Dynamic: license-file
